bdgd2opendss/__init__.py
bdgd2opendss/config/PRODIST_MOD7_TR_MONO_15kvmax.csv
bdgd2opendss/config/PRODIST_MOD7_TR_MONO_24.2kvmax.csv
bdgd2opendss/config/PRODIST_MOD7_TR_MONO_36.2kvmax.csv
bdgd2opendss/config/PRODIST_MOD7_TR_TRIF_15kvmax.csv
bdgd2opendss/config/PRODIST_MOD7_TR_TRIF_24.2kvmax.csv
bdgd2opendss/config/PRODIST_MOD7_TR_TRIF_36.2kvmax.csv
bdgd2opendss/config/__init__.py
bdgd2opendss/config/bdgd2dss.json
bdgd2opendss/config/bdgd2dss_error.json
bdgd2opendss/config/bdgd2dss_error_private.json
bdgd2opendss/config/bdgd2dss_private.json
bdgd2opendss/config/paths.py
bdgd2opendss/core/Core.py
bdgd2opendss/core/JsonData.py
bdgd2opendss/core/Settings.py
bdgd2opendss/core/Utils.py
bdgd2opendss/core/__init__.py
bdgd2opendss/error_messages/en.json
bdgd2opendss/error_messages/pt-br.json
bdgd2opendss/model/BusCoords.py
bdgd2opendss/model/Capacitor.py
bdgd2opendss/model/Case.py
bdgd2opendss/model/Circuit.py
bdgd2opendss/model/Converter.py
bdgd2opendss/model/Count_days.py
bdgd2opendss/model/EnergyMeters.py
bdgd2opendss/model/KVBase.py
bdgd2opendss/model/Line.py
bdgd2opendss/model/LineCode.py
bdgd2opendss/model/Load.py
bdgd2opendss/model/LoadShape.py
bdgd2opendss/model/PVsystem.py
bdgd2opendss/model/RegControl.py
bdgd2opendss/model/Transformer.py
bdgd2opendss/model/__init__.py
bdgd2opendss-1.0.1.dist-info/licenses/AUTHORS.rst
bdgd2opendss-1.0.1.dist-info/licenses/LICENSE
bdgd2opendss-1.0.1.dist-info/METADATA
bdgd2opendss-1.0.1.dist-info/WHEEL
bdgd2opendss-1.0.1.dist-info/top_level.txt
bdgd2opendss-1.0.1.dist-info/RECORD
